kbar/__init__.py
kbar/kbar.py
kbar-0.1.2.dist-info/licenses/LICENSE
kbar-0.1.2.dist-info/METADATA
kbar-0.1.2.dist-info/WHEEL
kbar-0.1.2.dist-info/top_level.txt
kbar-0.1.2.dist-info/RECORD
