Metadata-Version: 2.4
Name: kbar
Version: 0.1.2
Summary: A lightweight K-line (candlestick) plotting tool with matplotlib and mplfinance.
Author: Tony Y.H. Huang
License: 
Project-URL: Homepage, https://github.com/tony1966/kbar/
Project-URL: Bug Tracker, https://github.com/tony1966/kbar/issues
Keywords: finance,candlestick,mplfinance,k-line,stock
Classifier: Development Status :: 3 - Alpha
Classifier: Intended Audience :: Developers
Classifier: Intended Audience :: Financial and Insurance Industry
Classifier: Programming Language :: Python :: 3
Classifier: License :: OSI Approved :: MIT License
Classifier: Operating System :: OS Independent
Requires-Python: >=3.9
License-File: LICENSE
Requires-Dist: numpy<2,>=1.23
Requires-Dist: pandas<3.0,>=2.0
Requires-Dist: matplotlib<4.0,>=3.7
Requires-Dist: mplfinance>=0.12.10b0
Requires-Dist: pyarrow>=14.0.2
Provides-Extra: dev
Requires-Dist: pytest>=8.0; extra == "dev"
Requires-Dist: coverage>=7.0; extra == "dev"
Dynamic: license-file
